README.rst
setup.cfg
setup.py
onesignalapi/__init__.py
onesignalapi.egg-info/PKG-INFO
onesignalapi.egg-info/SOURCES.txt
onesignalapi.egg-info/dependency_links.txt
onesignalapi.egg-info/requires.txt
onesignalapi.egg-info/top_level.txt
onesignalapi/config/__init__.py
onesignalapi/config/settings.py
onesignalapi/devices/__init__.py
onesignalapi/devices/device.py
onesignalapi/notifications/__init__.py
onesignalapi/notifications/notification.py
onesignalapi/utils/__init__.py
onesignalapi/utils/device_switcher.py
onesignalapi/utils/http_request.py
onesignalapi/utils/response.py
onesignalapi/utils/validator.py