Metadata-Version: 1.1
Name: onesignalapi
Version: 0.4
Summary: One Signal API SDK https://onesignal.com
Home-page: https://github.com/alexromer0/onesignal-api.git
Author: Alejandro Romero
Author-email: ealejandrorg@gmail.com
License: MIT
Download-URL: https://github.com/alexromer0/onesignal-api.git/tarball/0.4
Keywords: OneSignal,Notifications,Push
Platform: UNKNOWN
Classifier: Development Status :: 3 - Alpha
Classifier: Intended Audience :: Developers
Classifier: Topic :: Software Development :: Build Tools
Classifier: License :: OSI Approved :: MIT License
Classifier: Programming Language :: Python :: 2.6
Classifier: Programming Language :: Python :: 2.7
